{
  "ATENTIE!": "ORDINEA IN CARE APAR NUMELE IN ACEST FISIER ESTE IRELEVANTA, EI SUNT MEREU SORTATI ALFABETIC PE PAGINA",
  "profesori": {
    "content": [
      {
        "nume": "ABRUDAN G IOAN"
      },
      {
        "nume": "ALBERT I MARIAN"
      },
      {
        "nume": "BALOGH - LUCIAN"
      },
      {
        "nume": "BODA S SZILÁRD"
      },
      {
        "nume": "BRIȘAN ETS MARTA"
      },
      {
        "nume": "BULGĂREAN G GHEORGHE VASILE"
      },
      {
        "nume": "BULGĂREAN I SANDA"
      },
      {
        "nume": "CHERECHEȘ A RODICA SIMONA"
      },
      {
        "nume": "CHINȚA D LIGIA IMELDA"
      },
      {
        "nume": "CHIȘ G MIRELA"
      },
      {
        "nume": "CHIȘ I PAUL-ADRIAN"
      },
      {
        "nume": "CIOCAN A DANA MARIA"
      },
      {
        "nume": "CIRȚI I RALUCA-CRISTINA"
      },
      {
        "nume": "CORNEA IF IOANA MIHAELA"
      },
      {
        "nume": "COSTEA N VALERIA"
      },
      {
        "nume": "COTOI G ALINA-RAMONA"
      },
      {
        "nume": "CRIȘAN G GABRIELA CLARA"
      },
      {
        "nume": "DAN N CLARA"
      },
      {
        "nume": "DEAC A PAULA CRISTINA"
      },
      {
        "nume": "DOSPINESCU I LIANA"
      },
      {
        "nume": "DUMA I SANDA"
      },
      {
        "nume": "FALUVÉGI FZ ERVIN ZOLTÁN"
      },
      {
        "nume": "FAUR A ILDIKÓ ANDREA"
      },
      {
        "nume": "FAZAKAS S ISTVÁN LEVENTE"
      },
      {
        "nume": "FLORIAN G IULIA VIORICA"
      },
      {
        "nume": "FORRÓ A ZOLTÁN LEVENTE"
      },
      {
        "nume": "FORȚ I CORINA EMILIA"
      },
      {
        "nume": "GÁSPÁR F EDIT"
      },
      {
        "nume": "GÂRBOAN V FLORICA-MIHAELA"
      },
      {
        "nume": "GOGA V LUCIAN MARIUS"
      },
      {
        "nume": "GORGAN I DANIELA"
      },
      {
        "nume": "IANCHIS T ALINA"
      },
      {
        "nume": "IEPURE I IOANA"
      },
      {
        "nume": "ILONȚA I ANDREI DAN"
      },
      {
        "nume": "ISA P LAVINIA MARCELA"
      },
      {
        "nume": "LÁSZLÓ G JUDIT"
      },
      {
        "nume": "LUCACIU D SIMONA-DANIELA"
      },
      {
        "nume": "MAN A CRISTIAN-MARIUS"
      },
      {
        "nume": "MARIAN T ADRIANA CLAUDIA"
      },
      {
        "nume": "MARINCAȘ I CĂLIN-VALERIU"
      },
      {
        "nume": "MATEI V MARIUS-VASILE"
      },
      {
        "nume": "MATYAS M EVA"
      },
      {
        "nume": "MĂCELAR-MUTU C LIVIU-ALIN"
      },
      {
        "nume": "MOCAN GD PAULA"
      },
      {
        "nume": "MORAR R FLORIN"
      },
      {
        "nume": "MORAR V MONICA"
      },
      {
        "nume": "NAGY FG FERENCZ"
      },
      {
        "nume": "OLAR C GABRIELA CARMEN"
      },
      {
        "nume": "ORBAN F TIMEA-GABRIELLA"
      },
      {
        "nume": "PĂȘTEAN A CAMELIA DELIA"
      },
      {
        "nume": "POP M EMILIA"
      },
      {
        "nume": "POP Ș ȘTEFANIA ANTONETA"
      },
      {
        "nume": "POP V MARIANA EMILIA"
      },
      {
        "nume": "RAD N CIPRIAN-VASILE"
      },
      {
        "nume": "REVNIC T GHEORGHE"
      },
      {
        "nume": "STROIA P MARIUS DANIEL"
      },
      {
        "nume": "SZABÓ I KATALIN"
      },
      {
        "nume": "SZÉLES A BEÁTA"
      },
      {
        "nume": "ȘIMON Z AMÁLIA"
      },
      {
        "nume": "TARR I ADORJAN"
      },
      {
        "nume": "TOBIAS T ISTVÁN TAMÁS"
      },
      {
        "nume": "TŐTŐS J ZOLTÁN JANÓS"
      },
      {
        "nume": "TUDUCE I IOANA MARIA"
      },
      {
        "nume": "TURCU V MIHAELA ANCA"
      },
      {
        "nume": "TURDEAN A KATALIN ZSUZSANA"
      },
      {
        "nume": "ȚÂRLE Ș MONICA"
      },
      {
        "nume": "ȚICALĂ G MARIA"
      },
      {
        "nume": "VAIDA A DIANA-MARIA"
      },
      {
        "nume": "VLAICU I CRISTINA IOANA"
      }









    ]
  }

}